my_package/__init__.py
my_package/math_utils.py
adams_academy-0.1.0.dist-info/LICENSE.txt
adams_academy-0.1.0.dist-info/METADATA
adams_academy-0.1.0.dist-info/WHEEL
adams_academy-0.1.0.dist-info/top_level.txt
adams_academy-0.1.0.dist-info/RECORD
